{
  "title": "Bel-Air Infinity Edge Pool",
  "location": "Bel-Air, CA",
  "neighborhood": "Bel-Air",
  "category": "Pool",
  "completionYear": "2024",
  "squareFootage": "1,800",
  "description": "Resort-caliber custom pool construction in the heart of Bel-Air. This infinity edge pool with integrated spa delivers panoramic canyon views, automated LED lighting, and custom limestone decking. A showpiece outdoor environment designed to entertain at scale while remaining effortlessly low-maintenance.",
  "tags": ["custom pool construction", "infinity pool", "Bel-Air", "outdoor living", "resort style", "spa"]
}
